qwhatyTuring/__init__.py
qwhatyTuring/diagrams.py
qwhatyTuring/exceptions.py
qwhatyTuring/graphicsDisplay.py
qwhatyTuring/interpreter.py
qwhatyTuring-1.1.0.dist-info/LICENSE
qwhatyTuring-1.1.0.dist-info/METADATA
qwhatyTuring-1.1.0.dist-info/WHEEL
qwhatyTuring-1.1.0.dist-info/top_level.txt
qwhatyTuring-1.1.0.dist-info/RECORD
