Metadata-Version: 2.1
Name: qwhatyTuring
Version: 1.1.0
Summary: Turing Machine in Python
Home-page: https://github.com/qwhaty/Python-Turing-Machine
Author: qwhaty
Author-email: qwhaty@hotmail.com
License: MIT
Classifier: Intended Audience :: Education
Classifier: Topic :: Education
Classifier: License :: OSI Approved :: MIT License
Classifier: Programming Language :: Python :: 3.10
Classifier: Programming Language :: Python :: 3.11
License-File: LICENSE
Requires-Dist: pygame
